README
setup.py
oldowan/__init__.py
oldowan.mitomotifs_cmdline.egg-info/PKG-INFO
oldowan.mitomotifs_cmdline.egg-info/SOURCES.txt
oldowan.mitomotifs_cmdline.egg-info/dependency_links.txt
oldowan.mitomotifs_cmdline.egg-info/entry_points.txt
oldowan.mitomotifs_cmdline.egg-info/namespace_packages.txt
oldowan.mitomotifs_cmdline.egg-info/requires.txt
oldowan.mitomotifs_cmdline.egg-info/top_level.txt
oldowan.mitomotifs_cmdline.egg-info/zip-safe
oldowan/mitomotifs_cmdline/__init__.py
oldowan/mitomotifs_cmdline/seq2sites.py
oldowan/mitomotifs_cmdline/sites2seq.py
