Metadata-Version: 1.0
Name: oldowan.mitomotifs-cmdline
Version: 1.0.0
Summary: Command line scripts for the oldowan.mitomotifs package.
